mastercode/__init__.py
mastercode/mastercode.py
mastercode-1.1.dist-info/LICENSE
mastercode-1.1.dist-info/METADATA
mastercode-1.1.dist-info/WHEEL
mastercode-1.1.dist-info/top_level.txt
mastercode-1.1.dist-info/RECORD
